otf2-3.1.1.dist-info/RECORD
otf2-3.1.1.dist-info/top_level.txt
otf2-3.1.1.dist-info/METADATA
otf2-3.1.1.dist-info/COPYING
otf2-3.1.1.dist-info/WHEEL
_otf2/SnapReaderCallbacks.py
_otf2/Marker.py
_otf2/Reader.py
_otf2/GlobalDefWriter.py
_otf2/MarkerReaderCallbacks.py
_otf2/ErrorCodes.py
_otf2/AttributeValue.py
_otf2/Thumbnail.py
_otf2/AttributeList.py
_otf2/Definitions.py
_otf2/IdMap.py
_otf2/GeneralDefinitions.py
_otf2/Callbacks.py
_otf2/Archive.py
_otf2/MarkerReader.py
_otf2/GlobalSnapReader.py
_otf2/GlobalDefReaderCallbacks.py
_otf2/GlobalEvtReaderCallbacks.py
_otf2/EventSizeEstimator.py
_otf2/DefWriter.py
_otf2/EvtReaderCallbacks.py
_otf2/SnapWriter.py
_otf2/Config.py
_otf2/DefReader.py
_otf2/_otf2.cpython-38-i386-linux-gnu.so
_otf2/EvtWriter.py
_otf2/GlobalDefReader.py
_otf2/SnapReader.py
_otf2/__init__.py
_otf2/GlobalSnapReaderCallbacks.py
_otf2/DefReaderCallbacks.py
_otf2/Events.py
_otf2/GlobalEvtReader.py
_otf2/EvtReader.py
_otf2/MarkerWriter.py
otf2/events.py
otf2/error.py
otf2/definitions.py
otf2/registry.py
otf2/writer.py
otf2/attribute_list.py
otf2/event_reader.py
otf2/definition_writer.py
otf2/reader.py
otf2/event_writer.py
otf2/attribute_value.py
otf2/__init__.py
otf2/enums.py
