Metadata-Version: 2.1
Name: otf2
Version: 3.1.1
Summary: OTF2 - The Open Trace Format Version 2
Home-page: https://score-p.org/
Author: The Score-P development team
Author-email: support@score-p.org
License: BSD-3
Project-URL: Documentation, https://perftools.pages.jsc.fz-juelich.de/cicd/otf2/tags/latest/python/
Platform: UNKNOWN
Classifier: License :: OSI Approved :: BSD License
Classifier: Development Status :: 5 - Production/Stable
Classifier: Natural Language :: English
Classifier: Operating System :: POSIX :: Linux
Classifier: Programming Language :: Python :: 3
Classifier: Programming Language :: Python :: 3.6
Classifier: Programming Language :: Python :: 3.7
Classifier: Programming Language :: Python :: 3.8
Classifier: Programming Language :: Python :: 3.9
Classifier: Programming Language :: Python :: 3.10
Classifier: Programming Language :: Python :: 3.11
Classifier: Programming Language :: C
Classifier: Topic :: Software Development :: Libraries
Classifier: Topic :: System :: Monitoring
Requires-Python: >=3.6
License-File: COPYING
